moco_wrapper/__init__.py
moco_wrapper/moco.py
moco_wrapper/exceptions/__init__.py
moco_wrapper/exceptions/base.py
moco_wrapper/exceptions/forbidden.py
moco_wrapper/exceptions/not_found.py
moco_wrapper/exceptions/rate_limit.py
moco_wrapper/exceptions/server_error.py
moco_wrapper/exceptions/unauthorized.py
moco_wrapper/exceptions/unprocessable.py
moco_wrapper/models/__init__.py
moco_wrapper/models/account_fixed_cost.py
moco_wrapper/models/account_hourly_rate.py
moco_wrapper/models/account_internal_hourly_rate.py
moco_wrapper/models/activity.py
moco_wrapper/models/base.py
moco_wrapper/models/comment.py
moco_wrapper/models/company.py
moco_wrapper/models/contact.py
moco_wrapper/models/deal.py
moco_wrapper/models/deal_category.py
moco_wrapper/models/invoice.py
moco_wrapper/models/invoice_payment.py
moco_wrapper/models/offer.py
moco_wrapper/models/planning_entry.py
moco_wrapper/models/project.py
moco_wrapper/models/project_contract.py
moco_wrapper/models/project_expense.py
moco_wrapper/models/project_payment_schedule.py
moco_wrapper/models/project_recurring_expense.py
moco_wrapper/models/project_task.py
moco_wrapper/models/purchase.py
moco_wrapper/models/purchase_category.py
moco_wrapper/models/purchase_draft.py
moco_wrapper/models/report.py
moco_wrapper/models/schedule.py
moco_wrapper/models/session.py
moco_wrapper/models/tagging.py
moco_wrapper/models/unit.py
moco_wrapper/models/user.py
moco_wrapper/models/user_employment.py
moco_wrapper/models/user_holiday.py
moco_wrapper/models/user_presence.py
moco_wrapper/models/objector_models/__init__.py
moco_wrapper/models/objector_models/account_fixed_cost.py
moco_wrapper/models/objector_models/account_hourly_rate.py
moco_wrapper/models/objector_models/account_internal_hourly_rate.py
moco_wrapper/models/objector_models/activity.py
moco_wrapper/models/objector_models/comment.py
moco_wrapper/models/objector_models/company.py
moco_wrapper/models/objector_models/contact.py
moco_wrapper/models/objector_models/deal.py
moco_wrapper-0.11.2.dist-info/AUTHORS.rst
moco_wrapper-0.11.2.dist-info/LICENSE
moco_wrapper-0.11.2.dist-info/METADATA
moco_wrapper-0.11.2.dist-info/WHEEL
moco_wrapper-0.11.2.dist-info/top_level.txt
moco_wrapper-0.11.2.dist-info/RECORD
