Metadata-Version: 2.1
Name: moco-wrapper
Version: 0.11.2
Summary: Wrapper package for using the moco api interface
Home-page: https://github.com/sommalia/moco-wrapper
Author: sommalia
Author-email: sommalia@protonmail.com
License: GNU General Public License v3
Keywords: moco_wrapper
Platform: UNKNOWN
Classifier: Development Status :: 3 - Alpha
Classifier: Intended Audience :: Developers
Classifier: License :: OSI Approved :: GNU General Public License v3 (GPLv3)
Classifier: Natural Language :: English
Classifier: Programming Language :: Python :: 3
Classifier: Programming Language :: Python :: 3.5
Classifier: Programming Language :: Python :: 3.6
Classifier: Programming Language :: Python :: 3.7
Requires-Python: >=3.5.0
Requires-Dist: requests
